adpbulk/__init__.py
adpbulk/adpbulk.py
adpbulk-0.1.4.dist-info/LICENSE
adpbulk-0.1.4.dist-info/WHEEL
adpbulk-0.1.4.dist-info/METADATA
adpbulk-0.1.4.dist-info/RECORD
