Metadata-Version: 2.1
Name: adpbulk
Version: 0.1.4
Summary: Pseudo-Bulking Single-Cell RNA-seq
Author-email: Noam Teyssier <noam.teyssier@ucsf.edu>
Classifier: License :: OSI Approved :: MIT License
Requires-Dist: anndata>=0.7.4
Requires-Dist: numpy>=1.17.0
Requires-Dist: pandas>=0.21
Requires-Dist: tqdm
Requires-Dist: pytest
Project-URL: Source, https://github.com/noamteyssier/adpbulk
